Metadata-Version: 1.1
Name: formbar
Version: 0.24.3
Summary: Python library to layout, render and validate HTML forms in web applications
Home-page: https://github.com/ringo-framework/formbar
Author: Torsten Irländer
Author-email: torsten@irlaender.de
License: GNU General Public License v2 or later (GPLv2+)
Keywords: form configuration layout rendering serialisation validation rules conditionals html
Platform: UNKNOWN
Classifier: Development Status :: 4 - Beta
Classifier: Intended Audience :: Developers
Classifier: License :: OSI Approved :: GNU General Public License v2 or later (GPLv2+)
Classifier: Programming Language :: Python :: 2.7
